<?xml version="1.0" encoding="UTF-8"?><?xml-stylesheet type='text/xsl' href='_UpgradeReport_Files/UpgradeReport.xslt'?><UpgradeLog>
<Properties><Property Name="Solution" Value="ProductSearch_V12">
</Property><Property Name="Solution File" Value="C:\Documents and Settings\Hyder\application\ProductSearch_V12.sln">
</Property><Property Name="Date" Value="Friday, March 09, 2012">
</Property><Property Name="Time" Value="22:19:00 PM">
</Property><Property Name="Log Number" Value="2">
</Property></Properties><Event ErrorLevel="0" Project="Unity" Source="UnitySource\Src\Unity\Unity.csproj" Description="Project file successfully backed up as C:\Documents and Settings\Hyder\application\Backup\Unity.csproj">
</Event><Event ErrorLevel="1" Project="Unity" Source="UnitySource\Src\Common\GlobalAssemblyInfo.cs" Description="Backed up project may not build.  Project contains linked file: C:\Documents and Settings\Hyder\application\Backup\GlobalAssemblyInfo.cs">
</Event><Event ErrorLevel="0" Project="Unity" Source="UnitySource\Src\Common\GlobalAssemblyInfo.cs" Description="File successfully backed up as C:\Documents and Settings\Hyder\application\Backup\GlobalAssemblyInfo.cs">
</Event><Event ErrorLevel="0" Project="Unity" Source="UnitySource\Src\Unity\Attributes\DependencyResolutionAttribute.cs" Description="File successfully backed up as C:\Documents and Settings\Hyder\application\Backup\Attributes\DependencyResolutionAttribute.cs">
</Event><Event ErrorLevel="0" Project="Unity" Source="UnitySource\Src\Unity\Attributes\InjectionConstructorAttribute.cs" Description="File successfully backed up as C:\Documents and Settings\Hyder\application\Backup\Attributes\InjectionConstructorAttribute.cs">
</Event><Event ErrorLevel="0" Project="Unity" Source="UnitySource\Src\Unity\Attributes\InjectionMethodAttribute.cs" Description="File successfully backed up as C:\Documents and Settings\Hyder\application\Backup\Attributes\InjectionMethodAttribute.cs">
</Event><Event ErrorLevel="0" Project="Unity" Source="UnitySource\Src\Unity\Attributes\DependencyAttribute.cs" Description="File successfully backed up as C:\Documents and Settings\Hyder\application\Backup\Attributes\DependencyAttribute.cs">
</Event><Event ErrorLevel="0" Project="Unity" Source="UnitySource\Src\Unity\Extension\ExtensionContext.cs" Description="File successfully backed up as C:\Documents and Settings\Hyder\application\Backup\Extension\ExtensionContext.cs">
</Event><Event ErrorLevel="0" Project="Unity" Source="UnitySource\Src\Unity\Extension\IUnityContainerExtensionConfigurator.cs" Description="File successfully backed up as C:\Documents and Settings\Hyder\application\Backup\Extension\IUnityContainerExtensionConfigurator.cs">
</Event><Event ErrorLevel="0" Project="Unity" Source="UnitySource\Src\Unity\Extension\NamedEventArgs.cs" Description="File successfully backed up as C:\Documents and Settings\Hyder\application\Backup\Extension\NamedEventArgs.cs">
</Event><Event ErrorLevel="0" Project="Unity" Source="UnitySource\Src\Unity\Extension\RegisterEventArgs.cs" Description="File successfully backed up as C:\Documents and Settings\Hyder\application\Backup\Extension\RegisterEventArgs.cs">
</Event><Event ErrorLevel="0" Project="Unity" Source="UnitySource\Src\Unity\Extension\RegisterInstanceEventArgs.cs" Description="File successfully backed up as C:\Documents and Settings\Hyder\application\Backup\Extension\RegisterInstanceEventArgs.cs">
</Event><Event ErrorLevel="0" Project="Unity" Source="UnitySource\Src\Unity\Extension\UnityContainerExtension.cs" Description="File successfully backed up as C:\Documents and Settings\Hyder\application\Backup\Extension\UnityContainerExtension.cs">
</Event><Event ErrorLevel="0" Project="Unity" Source="UnitySource\Src\Unity\GlobalSuppressions.cs" Description="File successfully backed up as C:\Documents and Settings\Hyder\application\Backup\GlobalSuppressions.cs">
</Event><Event ErrorLevel="0" Project="Unity" Source="UnitySource\Src\Unity\Injection\InjectedMembers.cs" Description="File successfully backed up as C:\Documents and Settings\Hyder\application\Backup\Injection\InjectedMembers.cs">
</Event><Event ErrorLevel="0" Project="Unity" Source="UnitySource\Src\Unity\Injection\InjectionConstructor.cs" Description="File successfully backed up as C:\Documents and Settings\Hyder\application\Backup\Injection\InjectionConstructor.cs">
</Event><Event ErrorLevel="0" Project="Unity" Source="UnitySource\Src\Unity\Injection\InjectionMember.cs" Description="File successfully backed up as C:\Documents and Settings\Hyder\application\Backup\Injection\InjectionMember.cs">
</Event><Event ErrorLevel="0" Project="Unity" Source="UnitySource\Src\Unity\Injection\InjectionMethod.cs" Description="File successfully backed up as C:\Documents and Settings\Hyder\application\Backup\Injection\InjectionMethod.cs">
</Event><Event ErrorLevel="0" Project="Unity" Source="UnitySource\Src\Unity\Injection\InjectionParameter.cs" Description="File successfully backed up as C:\Documents and Settings\Hyder\application\Backup\Injection\InjectionParameter.cs">
</Event><Event ErrorLevel="0" Project="Unity" Source="UnitySource\Src\Unity\Injection\InjectionParameterValue.cs" Description="File successfully backed up as C:\Documents and Settings\Hyder\application\Backup\Injection\InjectionParameterValue.cs">
</Event><Event ErrorLevel="0" Project="Unity" Source="UnitySource\Src\Unity\Injection\InjectionProperty.cs" Description="File successfully backed up as C:\Documents and Settings\Hyder\application\Backup\Injection\InjectionProperty.cs">
</Event><Event ErrorLevel="0" Project="Unity" Source="UnitySource\Src\Unity\IUnityContainer.cs" Description="File successfully backed up as C:\Documents and Settings\Hyder\application\Backup\IUnityContainer.cs">
</Event><Event ErrorLevel="0" Project="Unity" Source="UnitySource\Src\Unity\Lifetime\ContainerControlledLifetimeManager.cs" Description="File successfully backed up as C:\Documents and Settings\Hyder\application\Backup\Lifetime\ContainerControlledLifetimeManager.cs">
</Event><Event ErrorLevel="0" Project="Unity" Source="UnitySource\Src\Unity\Lifetime\ExternallyControlledLifetimeManager.cs" Description="File successfully backed up as C:\Documents and Settings\Hyder\application\Backup\Lifetime\ExternallyControlledLifetimeManager.cs">
</Event><Event ErrorLevel="0" Project="Unity" Source="UnitySource\Src\Unity\Lifetime\LifetimeManager.cs" Description="File successfully backed up as C:\Documents and Settings\Hyder\application\Backup\Lifetime\LifetimeManager.cs">
</Event><Event ErrorLevel="0" Project="Unity" Source="UnitySource\Src\Unity\Lifetime\LifetimeManagerFactory.cs" Description="File successfully backed up as C:\Documents and Settings\Hyder\application\Backup\Lifetime\LifetimeManagerFactory.cs">
</Event><Event ErrorLevel="0" Project="Unity" Source="UnitySource\Src\Unity\Lifetime\TransientLifetimeManager.cs" Description="File successfully backed up as C:\Documents and Settings\Hyder\application\Backup\Lifetime\TransientLifetimeManager.cs">
</Event><Event ErrorLevel="0" Project="Unity" Source="UnitySource\Src\Unity\ObjectBuilder\DefaultUnityConstructorSelectorPolicy.cs" Description="File successfully backed up as C:\Documents and Settings\Hyder\application\Backup\ObjectBuilder\DefaultUnityConstructorSelectorPolicy.cs">
</Event><Event ErrorLevel="0" Project="Unity" Source="UnitySource\Src\Unity\ObjectBuilder\DefaultUnityMethodSelectorPolicy.cs" Description="File successfully backed up as C:\Documents and Settings\Hyder\application\Backup\ObjectBuilder\DefaultUnityMethodSelectorPolicy.cs">
</Event><Event ErrorLevel="0" Project="Unity" Source="UnitySource\Src\Unity\ObjectBuilder\DefaultUnityPropertySelectorPolicy.cs" Description="File successfully backed up as C:\Documents and Settings\Hyder\application\Backup\ObjectBuilder\DefaultUnityPropertySelectorPolicy.cs">
</Event><Event ErrorLevel="0" Project="Unity" Source="UnitySource\Src\Unity\ObjectBuilder\LiteralValueDependencyResolverPolicy.cs" Description="File successfully backed up as C:\Documents and Settings\Hyder\application\Backup\ObjectBuilder\LiteralValueDependencyResolverPolicy.cs">
</Event><Event ErrorLevel="0" Project="Unity" Source="UnitySource\Src\Unity\ObjectBuilder\NamedTypeDependencyResolverPolicy.cs" Description="File successfully backed up as C:\Documents and Settings\Hyder\application\Backup\ObjectBuilder\NamedTypeDependencyResolverPolicy.cs">
</Event><Event ErrorLevel="0" Project="Unity" Source="UnitySource\Src\Unity\ObjectBuilder\SpecifiedConstructorSelectorPolicy.cs" Description="File successfully backed up as C:\Documents and Settings\Hyder\application\Backup\ObjectBuilder\SpecifiedConstructorSelectorPolicy.cs">
</Event><Event ErrorLevel="0" Project="Unity" Source="UnitySource\Src\Unity\ObjectBuilder\SpecifiedMemberSelectorHelper.cs" Description="File successfully backed up as C:\Documents and Settings\Hyder\application\Backup\ObjectBuilder\SpecifiedMemberSelectorHelper.cs">
</Event><Event ErrorLevel="0" Project="Unity" Source="UnitySource\Src\Unity\ObjectBuilder\SpecifiedMethodsSelectorPolicy.cs" Description="File successfully backed up as C:\Documents and Settings\Hyder\application\Backup\ObjectBuilder\SpecifiedMethodsSelectorPolicy.cs">
</Event><Event ErrorLevel="0" Project="Unity" Source="UnitySource\Src\Unity\ObjectBuilder\SpecifiedPropertiesSelectorPolicy.cs" Description="File successfully backed up as C:\Documents and Settings\Hyder\application\Backup\ObjectBuilder\SpecifiedPropertiesSelectorPolicy.cs">
</Event><Event ErrorLevel="0" Project="Unity" Source="UnitySource\Src\Unity\ResolutionFailedException.cs" Description="File successfully backed up as C:\Documents and Settings\Hyder\application\Backup\ResolutionFailedException.cs">
</Event><Event ErrorLevel="0" Project="Unity" Source="UnitySource\Src\Unity\Injection\ResolvedParameter.cs" Description="File successfully backed up as C:\Documents and Settings\Hyder\application\Backup\Injection\ResolvedParameter.cs">
</Event><Event ErrorLevel="0" Project="Unity" Source="UnitySource\Src\Unity\UnityContainerBase.cs" Description="File successfully backed up as C:\Documents and Settings\Hyder\application\Backup\UnityContainerBase.cs">
</Event><Event ErrorLevel="0" Project="Unity" Source="UnitySource\Src\Unity\Utility\Guard.cs" Description="File successfully backed up as C:\Documents and Settings\Hyder\application\Backup\Utility\Guard.cs">
</Event><Event ErrorLevel="0" Project="Unity" Source="UnitySource\Src\Unity\NamedTypesRegistry.cs" Description="File successfully backed up as C:\Documents and Settings\Hyder\application\Backup\NamedTypesRegistry.cs">
</Event><Event ErrorLevel="0" Project="Unity" Source="UnitySource\Src\Unity\ObjectBuilder\UnityBuildStage.cs" Description="File successfully backed up as C:\Documents and Settings\Hyder\application\Backup\ObjectBuilder\UnityBuildStage.cs">
</Event><Event ErrorLevel="0" Project="Unity" Source="UnitySource\Src\Unity\Properties\AssemblyInfo.cs" Description="File successfully backed up as C:\Documents and Settings\Hyder\application\Backup\Properties\AssemblyInfo.cs">
</Event><Event ErrorLevel="0" Project="Unity" Source="UnitySource\Src\Unity\Properties\Resources.Designer.cs" Description="File successfully backed up as C:\Documents and Settings\Hyder\application\Backup\Properties\Resources.Designer.cs">
</Event><Event ErrorLevel="0" Project="Unity" Source="UnitySource\Src\Unity\UnityContainer.cs" Description="File successfully backed up as C:\Documents and Settings\Hyder\application\Backup\UnityContainer.cs">
</Event><Event ErrorLevel="0" Project="Unity" Source="UnitySource\Src\Unity\UnityDefaultBehaviorExtension.cs" Description="File successfully backed up as C:\Documents and Settings\Hyder\application\Backup\UnityDefaultBehaviorExtension.cs">
</Event><Event ErrorLevel="0" Project="Unity" Source="UnitySource\Src\Unity\UnityDefaultStrategiesExtension.cs" Description="File successfully backed up as C:\Documents and Settings\Hyder\application\Backup\UnityDefaultStrategiesExtension.cs">
</Event><Event ErrorLevel="0" Project="Unity" Source="UnitySource\Src\Unity\Utility\Pair.cs" Description="File successfully backed up as C:\Documents and Settings\Hyder\application\Backup\Utility\Pair.cs">
</Event><Event ErrorLevel="0" Project="Unity" Source="UnitySource\Src\Unity\Utility\Sequence.cs" Description="File successfully backed up as C:\Documents and Settings\Hyder\application\Backup\Utility\Sequence.cs">
</Event><Event ErrorLevel="0" Project="Unity" Source="UnitySource\Src\Unity\Properties\Resources.resx" Description="File successfully backed up as C:\Documents and Settings\Hyder\application\Backup\Properties\Resources.resx">
</Event><Event ErrorLevel="0" Project="Unity" Source="UnitySource\Src\Unity\Unity.csproj" Description="Project converted successfully">
</Event><Event ErrorLevel="3" Project="Unity" Source="UnitySource\Src\Unity\Unity.csproj" Description="Converted">
</Event><Event ErrorLevel="0" Project="Unity" Source="UnitySource\Src\Unity\Unity.csproj" Description="Scan complete: Upgrade not required for project files.">
</Event></UpgradeLog>